Topsis/__init__.py
Topsis/__main__.py
topsis_Prince_3619-1.2.0.dist-info/LICENSE
topsis_Prince_3619-1.2.0.dist-info/METADATA
topsis_Prince_3619-1.2.0.dist-info/WHEEL
topsis_Prince_3619-1.2.0.dist-info/entry_points.txt
topsis_Prince_3619-1.2.0.dist-info/top_level.txt
topsis_Prince_3619-1.2.0.dist-info/RECORD
