Metadata-Version: 2.2
Name: topsis-Prince-3619
Version: 1.2.0
Summary: A Python package to implement the TOPSIS method for decision making.
Home-page: https://github.com/Prince-05/TOPSIS
Author: Prince
Author-email: pprince_be22@thapar.edu
Classifier: Programming Language :: Python :: 3
Classifier: License :: OSI Approved :: MIT License
Classifier: Operating System :: OS Independent
Requires-Python: >=3.6
License-File: LICENSE
Requires-Dist: numpy
Requires-Dist: pandas
Dynamic: author
Dynamic: author-email
Dynamic: classifier
Dynamic: description
Dynamic: description-content-type
Dynamic: home-page
Dynamic: requires-dist
Dynamic: requires-python
Dynamic: summary
